tinkercss/__init__.py
tinkercss/css_generator.py
tinkercss-0.3.0.dist-info/METADATA
tinkercss-0.3.0.dist-info/WHEEL
tinkercss-0.3.0.dist-info/top_level.txt
tinkercss-0.3.0.dist-info/RECORD
