Metadata-Version: 2.1
Name: tinkercss
Version: 0.3.0
Summary: A CSS-like styling tool for Tkinter applications
Classifier: Programming Language :: Python :: 3
Classifier: License :: OSI Approved :: MIT License
Classifier: Operating System :: OS Independent
